amcheck/__init__.py
amcheck/amcheck.py
amcheck-1.0.2.dist-info/LICENSE
amcheck-1.0.2.dist-info/METADATA
amcheck-1.0.2.dist-info/WHEEL
amcheck-1.0.2.dist-info/entry_points.txt
amcheck-1.0.2.dist-info/RECORD
