Metadata-Version: 2.3
Name: amcheck
Version: 1.0.2
Summary: amcheck is the program (and a library) to check, based on the symmetry arguments, whether a given material is an altermagnet.
License: MIT
Author: Andriy Smolyanyuk
Author-email: andriysmolyanyuk@gmail.com
Maintainer: Andriy Smolyanyuk
Maintainer-email: andriysmolyanyuk@gmail.com
Requires-Python: >=3.10,<4
Classifier: License :: OSI Approved :: MIT License
Classifier: Programming Language :: Python :: 3
Classifier: Programming Language :: Python :: 3.10
Classifier: Programming Language :: Python :: 3.11
Classifier: Programming Language :: Python :: 3.12
Classifier: Programming Language :: Python :: 3.13
Requires-Dist: Diophantine (>=0.2.0)
Requires-Dist: ase (>=3.22.1)
Requires-Dist: numpy (>=1.20.0)
Requires-Dist: spglib (>=2.5.0)
